flatlatex_gui/__init__.py
flatlatex_gui/gui.py
flatlatex_gui-0.4.dist-info/LICENSE
flatlatex_gui-0.4.dist-info/METADATA
flatlatex_gui-0.4.dist-info/WHEEL
flatlatex_gui-0.4.dist-info/entry_points.txt
flatlatex_gui-0.4.dist-info/top_level.txt
flatlatex_gui-0.4.dist-info/RECORD
